Workbook

Sheet README
A1: Investor onboarding drop-off: impact model
A2: Synthetic dataset - illustrative case study, not data from any real company
A4: Purpose | B4: Size the improvement opportunities found in the onboarding funnel and rank them for the roadmap.
A5: Sheets | B5: Funnel (stage conversion) | Lever data (segment vs benchmark) | Impact Model (formulas + scenarios) | Segments (reference)
A6: Colour legend | B6: Blue text = input taken from the analysis data | Black = formula | Green = link to another sheet | Yellow fill = assumption you can change
A7: How to use | B7: Change the yellow cells on 'Impact Model' (revenue per account, overlap haircut, share of gap closed, confidence, effort). Everything recalculates.
A8: Method | B8: Excess users lost = segment users x (benchmark conversion - segment conversion). Recovered users then still have to pass the remaining stages, so they are multiplied by the downstream conversion to first funding.
A9: Source of data | B9: data/processed/*.csv generated by src/analysis.py from the synthetic dataset (src/generate_dataset.py).
A10: Assumptions to validate | B10: Revenue per funded account, effort (person-weeks) and confidence are placeholders. Replace with finance and engineering estimates; validate recovery through A/B tests (docs/06_ab_test_plan.md).
A11: Known limits | B11: Levers overlap (a user can be low-end Android AND on a slow bank), so the total is reduced by an overlap haircut. L1a uses the overall downstream conversion; offline-KYC users convert worse at e-Sign, so it is slightly optimistic unless L1b is also delivered.

Sheet Funnel
A1: Onboarding funnel
A2: Blue = data from analysis. Black = formulas. Stage 8 completed = activated account.
A4: Stage # | B4: Stage | C4: Entered | D4: Completed | E4: Dropped | F4: Step conversion | G4: Cumulative (% of sign-ups) | H4: Lost (% of sign-ups)
A5: 1 | B5: Registration & OTP verification | C5: 20000 | D5: 18035 | E5: =C5-D5 -> 1965 | F5: =IF(C5=0,0,D5/C5) -> 0.90175 | G5: =D5/$C$5 -> 0.90175 | H5: =E5/$C$5 -> 0.09825
A6: 2 | B6: PAN & Aadhaar KYC | C6: 18035 | D6: 12650 | E6: =C6-D6 -> 5385 | F6: =IF(C6=0,0,D6/C6) -> 0.70141392 | G6: =D6/$C$5 -> 0.6325 | H6: =E6/$C$5 -> 0.26925
A7: 3 | B7: Bank account verification | C7: 12650 | D7: 10135 | E7: =C7-D7 -> 2515 | F7: =IF(C7=0,0,D7/C7) -> 0.80118577 | G7: =D7/$C$5 -> 0.50675 | H7: =E7/$C$5 -> 0.12575
A8: 4 | B8: Personal details & nominee | C8: 10135 | D8: 9308 | E8: =C8-D8 -> 827 | F8: =IF(C8=0,0,D8/C8) -> 0.91840158 | G8: =D8/$C$5 -> 0.4654 | H8: =E8/$C$5 -> 0.04135
A9: 5 | B9: Segment selection & income proof | C9: 9308 | D9: 8424 | E9: =C9-D9 -> 884 | F9: =IF(C9=0,0,D9/C9) -> 0.90502793 | G9: =D9/$C$5 -> 0.4212 | H9: =E9/$C$5 -> 0.0442
A10: 6 | B10: Selfie / IPV verification | C10: 8424 | D10: 7194 | E10: =C10-D10 -> 1230 | F10: =IF(C10=0,0,D10/C10) -> 0.8539886 | G10: =D10/$C$5 -> 0.3597 | H10: =E10/$C$5 -> 0.0615
A11: 7 | B11: e-Sign | C11: 7194 | D11: 6447 | E11: =C11-D11 -> 747 | F11: =IF(C11=0,0,D11/C11) -> 0.89616347 | G11: =D11/$C$5 -> 0.32235 | H11: =E11/$C$5 -> 0.03735
A12: 8 | B12: Account approval | C12: 6447 | D12: 5964 | E12: =C12-D12 -> 483 | F12: =IF(C12=0,0,D12/C12) -> 0.92508143 | G12: =D12/$C$5 -> 0.2982 | H12: =E12/$C$5 -> 0.02415
A13: 9 | B13: First funding | C13: 5964 | D13: 3462 | E13: =C13-D13 -> 2502 | F13: =IF(C13=0,0,D13/C13) -> 0.5804829 | G13: =D13/$C$5 -> 0.1731 | H13: =E13/$C$5 -> 0.1251
A14: 10 | B14: First trade | C14: 3462 | D14: 2428 | E14: =C14-D14 -> 1034 | F14: =IF(C14=0,0,D14/C14) -> 0.70132871 | G14: =D14/$C$5 -> 0.1214 | H14: =E14/$C$5 -> 0.0517
A17: Key metrics
B18: Total sign-ups | C18: =C5 -> 20000
B19: Activation rate (account approved) | C19: =G12 -> 0.2982
B20: Funded rate (first deposit) | C20: =G13 -> 0.1731
B21: First-trade rate | C21: =G14 -> 0.1214
B22: Biggest leak (stage with most users lost) | C22: =INDEX(B5:B14,MATCH(MAX(E5:E14),E5:E14,0)) -> PAN & Aadhaar KYC

Sheet Lever data
A1: Improvement levers: segment vs like-for-like benchmark
A2: Counts are inputs from the analysis (blue). Conversion, gap and excess users lost are formulas.
A4: Lever | B4: Opportunity | C4: Stage # | D4: Segment | E4: Segment entered | F4: Segment completed | G4: Benchmark entered | H4: Benchmark completed | I4: Segment conv. | J4: Benchmark conv. | K4: Gap (pp) | L4: Users lost in segment | M4: Excess users lost vs benchmark
A5: L1a | B5: Alternative KYC path for users whose Aadhaar is not linked to their mobile (KYC stage) | C5: 2 | D5: Aadhaar not linked to mobile | E5: 2196 | F5: 732 | G5: 15839 | H5: 11918 | I5: =F5/E5 -> 0.33333333 | J5: =H5/G5 -> 0.75244649 | K5: =(J5-I5)*100 -> 41.911316 | L5: =E5-F5 -> 1464 | M5: =ROUND(MAX(0,E5*(J5-I5)),0) -> 920
A6: L1b | B6: Offline-KYC users blocked at e-Sign (signature step) | C6: 7 | D6: Aadhaar not linked to mobile | E6: 446 | F6: 342 | G6: 6748 | H6: 6105 | I6: =F6/E6 -> 0.76681614 | J6: =H6/G6 -> 0.90471251 | K6: =(J6-I6)*100 -> 13.789636 | L6: =E6-F6 -> 104 | M6: =ROUND(MAX(0,E6*(J6-I6)),0) -> 62
A7: L2 | B7: Bank-verification fallback (UPI / cancelled-cheque upload) for problem banks | C7: 3 | D7: PNB, Bank of Baroda, Co-operative / other | E7: 3948 | F7: 2659 | G7: 8702 | H7: 7476 | I7: =F7/E7 -> 0.67350557 | J7: =H7/G7 -> 0.85911285 | K7: =(J7-I7)*100 -> 18.560728 | L7: =E7-F7 -> 1289 | M7: =ROUND(MAX(0,E7*(J7-I7)),0) -> 733
A8: L3 | B8: Save-and-resume with reminders for late-night KYC starters | C8: 2 | D8: Signed up 22:00-05:59 (DigiLocker-eligible) | E8: 1677 | F8: 1128 | G8: 14162 | H8: 10790 | I8: =F8/E8 -> 0.6726297 | J8: =H8/G8 -> 0.76189804 | K8: =(J8-I8)*100 -> 8.9268341 | L8: =E8-F8 -> 549 | M8: =ROUND(MAX(0,E8*(J8-I8)),0) -> 150
A9: L4 | B9: Assisted selfie / IPV capture for low-end Android, web and 55+ users | C9: 6 | D9: Low-end Android, web or age 55+ | E9: 3123 | F9: 2522 | G9: 5301 | H9: 4672 | I9: =F9/E9 -> 0.80755684 | J9: =H9/G9 -> 0.88134314 | K9: =(J9-I9)*100 -> 7.3786306 | L9: =E9-F9 -> 601 | M9: =ROUND(MAX(0,E9*(J9-I9)),0) -> 230
A10: L5 | B10: First-funding nudges (one-tap UPI, starter offer) for paid-social/influencer users | C10: 9 | D10: Influencer / YouTube and Meta / social ads | E10: 1402 | F10: 694 | G10: 4562 | H10: 2768 | I10: =F10/E10 -> 0.49500713 | J10: =H10/G10 -> 0.60675142 | K10: =(J10-I10)*100 -> 11.174429 | L10: =E10-F10 -> 708 | M10: =ROUND(MAX(0,E10*(J10-I10)),0) -> 157
A11: L6 | B11: Simplified income-proof upload for F&O seekers | C11: 5 | D11: Wants F&O | E11: 2725 | F11: 2264 | G11: 6583 | H11: 6160 | I11: =F11/E11 -> 0.83082569 | J11: =H11/G11 -> 0.93574358 | K11: =(J11-I11)*100 -> 10.491789 | L11: =E11-F11 -> 461 | M11: =ROUND(MAX(0,E11*(J11-I11)),0) -> 286
A13: Benchmark = rest of the base at the same stage; for L3 it is DigiLocker-eligible users who did not sign up late at night (like-for-like).

Sheet Impact Model
A1: Impact model: incremental funded accounts and revenue
A2: Yellow cells are assumptions to validate. Levers overlap, so totals are reduced by the overlap haircut.
B4: Months in sign-up window (1 Apr - 31 Aug 2026) | C4: 5
B5: Annual revenue per funded account (placeholder - replace with finance figure) | C5: 2000
B6: Overlap haircut (levers target overlapping users) | C6: 0.2
B8: Scenario | C8: Conservative | D8: Base | E8: Optimistic
B9: Share of the conversion gap closed by the fix | C9: 0.25 | D9: 0.5 | E9: 0.75
A12: Lever | B12: Opportunity | C12: Stage # | D12: Excess users lost vs benchmark | E12: Downstream conversion to first funding | F12: Confidence (BA estimate) | G12: Effort (person-weeks, BA estimate) | H12: Incr. funded / month: Conservative | I12: Incr. funded / month: Base | J12: Incr. funded / month: Optimistic | K12: Priority score (Base x confidence / effort) | L12: Rank
A13: ='Lever data'!A5 -> L1a | B13: ='Lever data'!B5 -> Alternative KYC path for users whose Aadhaar is not linked to their mobile (KYC stage) | C13: ='Lever data'!C5 -> 2 | D13: ='Lever data'!M5 -> 920 | E13: =IF(C13>=9,1,PRODUCT(INDEX(Funnel!$F$5:$F$14,C13+1):INDEX(Funnel!$F$5:$F$14,9))) -> 0.27367589 | F13: 0.7 | G13: 12 | H13: =D13*$C$9*E13/$C$4 -> 12.589091 | I13: =D13*$D$9*E13/$C$4 -> 25.178182 | J13: =D13*$E$9*E13/$C$4 -> 37.767273 | K13: =I13*F13/G13 -> 1.4687273 | L13: =RANK(K13,$K$13:$K$19) -> 4
A14: ='Lever data'!A6 -> L1b | B14: ='Lever data'!B6 -> Offline-KYC users blocked at e-Sign (signature step) | C14: ='Lever data'!C6 -> 7 | D14: ='Lever data'!M6 -> 62 | E14: =IF(C14>=9,1,PRODUCT(INDEX(Funnel!$F$5:$F$14,C14+1):INDEX(Funnel!$F$5:$F$14,9))) -> 0.53699395 | F14: 0.6 | G14: 4 | H14: =D14*$C$9*E14/$C$4 -> 1.6646812 | I14: =D14*$D$9*E14/$C$4 -> 3.3293625 | J14: =D14*$E$9*E14/$C$4 -> 4.9940437 | K14: =I14*F14/G14 -> 0.49940437 | L14: =RANK(K14,$K$13:$K$19) -> 7
A15: ='Lever data'!A7 -> L2 | B15: ='Lever data'!B7 -> Bank-verification fallback (UPI / cancelled-cheque upload) for problem banks | C15: ='Lever data'!C7 -> 3 | D15: ='Lever data'!M7 -> 733 | E15: =IF(C15>=9,1,PRODUCT(INDEX(Funnel!$F$5:$F$14,C15+1):INDEX(Funnel!$F$5:$F$14,9))) -> 0.34158855 | F15: 0.7 | G15: 6 | H15: =D15*$C$9*E15/$C$4 -> 12.519221 | I15: =D15*$D$9*E15/$C$4 -> 25.038441 | J15: =D15*$E$9*E15/$C$4 -> 37.557662 | K15: =I15*F15/G15 -> 2.9211515 | L15: =RANK(K15,$K$13:$K$19) -> 1
A16: ='Lever data'!A8 -> L3 | B16: ='Lever data'!B8 -> Save-and-resume with reminders for late-night KYC starters | C16: ='Lever data'!C8 -> 2 | D16: ='Lever data'!M8 -> 150 | E16: =IF(C16>=9,1,PRODUCT(INDEX(Funnel!$F$5:$F$14,C16+1):INDEX(Funnel!$F$5:$F$14,9))) -> 0.27367589 | F16: 0.5 | G16: 3 | H16: =D16*$C$9*E16/$C$4 -> 2.0525692 | I16: =D16*$D$9*E16/$C$4 -> 4.1051383 | J16: =D16*$E$9*E16/$C$4 -> 6.1577075 | K16: =I16*F16/G16 -> 0.68418972 | L16: =RANK(K16,$K$13:$K$19) -> 6
A17: ='Lever data'!A9 -> L4 | B17: ='Lever data'!B9 -> Assisted selfie / IPV capture for low-end Android, web and 55+ users | C17: ='Lever data'!C9 -> 6 | D17: ='Lever data'!M9 -> 230 | E17: =IF(C17>=9,1,PRODUCT(INDEX(Funnel!$F$5:$F$14,C17+1):INDEX(Funnel!$F$5:$F$14,9))) -> 0.48123436 | F17: 0.6 | G17: 5 | H17: =D17*$C$9*E17/$C$4 -> 5.5341952 | I17: =D17*$D$9*E17/$C$4 -> 11.06839 | J17: =D17*$E$9*E17/$C$4 -> 16.602585 | K17: =I17*F17/G17 -> 1.3282068 | L17: =RANK(K17,$K$13:$K$19) -> 5
A18: ='Lever data'!A10 -> L5 | B18: ='Lever data'!B10 -> First-funding nudges (one-tap UPI, starter offer) for paid-social/influencer users | C18: ='Lever data'!C10 -> 9 | D18: ='Lever data'!M10 -> 157 | E18: =IF(C18>=9,1,PRODUCT(INDEX(Funnel!$F$5:$F$14,C18+1):INDEX(Funnel!$F$5:$F$14,9))) -> 1 | F18: 0.4 | G18: 3 | H18: =D18*$C$9*E18/$C$4 -> 7.85 | I18: =D18*$D$9*E18/$C$4 -> 15.7 | J18: =D18*$E$9*E18/$C$4 -> 23.55 | K18: =I18*F18/G18 -> 2.0933333 | L18: =RANK(K18,$K$13:$K$19) -> 2
A19: ='Lever data'!A11 -> L6 | B19: ='Lever data'!B11 -> Simplified income-proof upload for F&O seekers | C19: ='Lever data'!C11 -> 5 | D19: ='Lever data'!M11 -> 286 | E19: =IF(C19>=9,1,PRODUCT(INDEX(Funnel!$F$5:$F$14,C19+1):INDEX(Funnel!$F$5:$F$14,9))) -> 0.41096866 | F19: 0.6 | G19: 4 | H19: =D19*$C$9*E19/$C$4 -> 5.8768519 | I19: =D19*$D$9*E19/$C$4 -> 11.753704 | J19: =D19*$E$9*E19/$C$4 -> 17.630556 | K19: =I19*F19/G19 -> 1.7630556 | L19: =RANK(K19,$K$13:$K$19) -> 3
B20: Total (before overlap haircut) | H20: =SUM(H13:H19) -> 48.086609 | I20: =SUM(I13:I19) -> 96.173218 | J20: =SUM(J13:J19) -> 144.25983
B21: After overlap haircut: incremental funded accounts per month | H21: =H20*(1-$C$6) -> 38.469287 | I21: =I20*(1-$C$6) -> 76.938574 | J21: =J20*(1-$C$6) -> 115.40786
B22: Current funded accounts per month (from the data) | H22: =Funnel!$D$13/$C$4 -> 692.4 | I22: =Funnel!$D$13/$C$4 -> 692.4 | J22: =Funnel!$D$13/$C$4 -> 692.4
B23: Uplift in monthly funded accounts | H23: =H21/H22 -> 0.05555934 | I23: =I21/I22 -> 0.11111868 | J23: =J21/J22 -> 0.16667802
B24: Incremental revenue in the first year of operation (Rs) | H24: =H21*12*$C$5 -> 923262.89 | I24: =I21*12*$C$5 -> 1846525.8 | J24: =J21*12*$C$5 -> 2769788.7
B26: Notes
B27: 1. Excess users lost comes from the data; the recovered share is an assumption (row 9) to be validated through A/B tests.
B28: 2. Revenue per funded account, confidence and effort are placeholders. Replace them with finance and engineering estimates before using the ranking in a decision.
B29: 3. First-year revenue assumes each month's recovered accounts earn the annual revenue per account, which ignores ramp-up and churn.
B30: 4. Funded accounts (not just activated ones) are used because they are the accounts that generate revenue.

Sheet Segments
A1: Activation, funding and first-trade rate by segment
A2: Counts are inputs (blue). Rates and gaps are formulas. Gap = activation rate minus the overall rate, in percentage points.
A3: Overall activation rate | C3: =Funnel!C19 -> 0.2982
A5: Segment type | B5: Segment | C5: Users | D5: Activated | E5: Funded | F5: First trade | G5: Activation rate | H5: Funded rate | I5: Activation gap vs overall (pp) | J5: Share of sign-ups
A6: Channel | B6: Google Ads | C6: 4393 | D6: 1315 | E6: 755 | F6: 529 | G6: =D6/C6 -> 0.29933986 | H6: =E6/C6 -> 0.17186433 | I6: =(G6-$C$3)*100 -> 0.11398589 | J6: =C6/Funnel!$C$5 -> 0.21965
A7: Channel | B7: Influencer / YouTube | C7: 3552 | D7: 949 | E7: 475 | F7: 316 | G7: =D7/C7 -> 0.26717342 | H7: =E7/C7 -> 0.13372748 | I7: =(G7-$C$3)*100 -> -3.1026577 | J7: =C7/Funnel!$C$5 -> 0.1776
A8: Channel | B8: Meta / social ads | C8: 1587 | D8: 453 | E8: 219 | F8: 143 | G8: =D8/C8 -> 0.28544423 | H8: =E8/C8 -> 0.13799622 | I8: =(G8-$C$3)*100 -> -1.2755766 | J8: =C8/Funnel!$C$5 -> 0.07935
A9: Channel | B9: Organic | C9: 5649 | D9: 1676 | E9: 990 | F9: 709 | G9: =D9/C9 -> 0.29668968 | H9: =E9/C9 -> 0.17525226 | I9: =(G9-$C$3)*100 -> -0.15103204 | J9: =C9/Funnel!$C$5 -> 0.28245
A10: Channel | B10: Partner / sub-broker | C10: 1983 | D10: 637 | E10: 391 | F10: 285 | G10: =D10/C10 -> 0.32123046 | H10: =E10/C10 -> 0.197176 | I10: =(G10-$C$3)*100 -> 2.3030459 | J10: =C10/Funnel!$C$5 -> 0.09915
A11: Channel | B11: Referral | C11: 2836 | D11: 934 | E11: 632 | F11: 446 | G11: =D11/C11 -> 0.32933709 | H11: =E11/C11 -> 0.22284908 | I11: =(G11-$C$3)*100 -> 3.1137094 | J11: =C11/Funnel!$C$5 -> 0.1418
A12: Device OS | B12: Android | C12: 14456 | D12: 4141 | E12: 2383 | F12: 1631 | G12: =D12/C12 -> 0.28645545 | H12: =E12/C12 -> 0.16484505 | I12: =(G12-$C$3)*100 -> -1.1744549 | J12: =C12/Funnel!$C$5 -> 0.7228
A13: Device OS | B13: Web | C13: 2005 | D13: 618 | E13: 368 | F13: 267 | G13: =D13/C13 -> 0.30822943 | H13: =E13/C13 -> 0.18354115 | I13: =(G13-$C$3)*100 -> 1.0029426 | J13: =C13/Funnel!$C$5 -> 0.10025
A14: Device OS | B14: iOS | C14: 3539 | D14: 1205 | E14: 711 | F14: 530 | G14: =D14/C14 -> 0.34049166 | H14: =E14/C14 -> 0.20090421 | I14: =(G14-$C$3)*100 -> 4.2291664 | J14: =C14/Funnel!$C$5 -> 0.17695
A15: Device tier | B15: Desktop | C15: 2005 | D15: 618 | E15: 368 | F15: 267 | G15: =D15/C15 -> 0.30822943 | H15: =E15/C15 -> 0.18354115 | I15: =(G15-$C$3)*100 -> 1.0029426 | J15: =C15/Funnel!$C$5 -> 0.10025
A16: Device tier | B16: High-end | C16: 5457 | D16: 1827 | E16: 1073 | F16: 797 | G16: =D16/C16 -> 0.33479934 | H16: =E16/C16 -> 0.19662818 | I16: =(G16-$C$3)*100 -> 3.659934 | J16: =C16/Funnel!$C$5 -> 0.27285
A17: Device tier | B17: Low-end | C17: 5875 | D17: 1453 | E17: 824 | F17: 586 | G17: =D17/C17 -> 0.24731915 | H17: =E17/C17 -> 0.14025532 | I17: =(G17-$C$3)*100 -> -5.0880851 | J17: =C17/Funnel!$C$5 -> 0.29375
... A46: Campaign day | B46: Normal day | C46: 18066 | D46: 5410 | E46: 3128 | F46: 2192 | G46: =D46/C46 -> 0.29945754 | H46: =E46/C46 -> 0.17314292 | I46: =(G46-$C$3)*100 -> 0.12575446 | J46: =C46/Funnel!$C$5 -> 0.9033
